{
  "Version": "1.1",
  "ModID": "Spice_Ruins",
  "IncompatibleIds": null,
  "ModDependencies": null,
  "Category": {
    "Chinese": "多人游戏",
    "English": "Multiplayer",
    "French": null,
    "German": "Mehrspieler",
    "Italian": null,
    "Japanese": null,
    "Korean": null,
    "Polish": null,
    "Russian": null,
    "Spanish": null,
    "Taiwanese": null
  },
  "ModName": {
    "Chinese": "接管的岛屿是废墟",
    "English": "Ruins on island takeover",
    "French": null,
    "German": "Ruinen bei Inselübernahmen",
    "Italian": null,
    "Japanese": null,
    "Korean": null,
    "Polish": null,
    "Russian": null,
    "Spanish": null,
    "Taiwanese": null
  },
  "Description": {
    "Chinese": "当一个岛屿被占领时，所有的建筑都变成了废墟。",
    "English": "When an island is taken over, all the buildings persist as a ruin.",
    "French": null,
    "German": "Wenn eine Insel Übernommen wird, bleiben alle Gebäude als Ruine erhalten.",
    "Italian": null,
    "Japanese": null,
    "Korean": null,
    "Polish": null,
    "Russian": null,
    "Spanish": null,
    "Taiwanese": null
  },
  "KnownIssues": [
    {
      "Chinese": "",
      "English": "The AI might run into problems when taking over a player's island.",
      "French": null,
      "German": "Die KI kann Probleme bekommen, wenn sie die Insel eines Spielers übernimmt.",
      "Italian": null,
      "Japanese": null,
      "Korean": null,
      "Polish": null,
      "Russian": null,
      "Spanish": null,
      "Taiwanese": null
    }
  ],
  "DLCDependencies": null,
  "CreatorName": "Spice it up-Team: Taubenangriff",
  "CreatorContact": "https://discord.gg/YTQGDFK",
  "Image" : null,
  "ModioResourceId" : 3289420
}