{
  "Version": "1",
  "ModID": "Spice_Pausemode",
  "IncompatibleIds": null,
  "ModDependencies": null,
  "Category": {
    "Chinese": null,
    "English": "Addon",
    "French": null,
    "German": "Addon",
    "Italian": null,
    "Japanese": null,
    "Korean": null,
    "Polish": "Dodatek",
    "Russian": null,
    "Spanish": null,
    "Taiwanese": null
  },
  "ModName": {
    "Chinese": null,
    "English": "Active Pause",
    "French": null,
    "German": "Aktiver Pausenmods",
    "Italian": null,
    "Japanese": null,
    "Korean": null,
    "Polish": "Aktywna pauza",
    "Russian": null,
    "Spanish": null,
    "Taiwanese": null
  },
  "Description": {
    "Chinese": null,
    "English": "Adds an active pause to the game, which can be toggled with a customizable hotkey",
    "French": null,
    "German": "Fügt eine aktive Pause ein, die über einen einstellbaren Hotkey aktiviert werden kann.",
    "Italian": null,
    "Japanese": null,
    "Korean": null,
    "Polish": "Dodaje aktywną pauzę do gry, którą można przełączać za pomocą dostosowywalnego klawisza skrótu",
    "Russian": null,
    "Spanish": null,
    "Taiwanese": null
  },
  "KnownIssues": null,
  "DLCDependencies": null,
  "CreatorName": "Spice it up-Team: kskudlik",
  "CreatorContact": "https://discord.gg/YTQGDFK",
  "Image" : null
}